meanlib/__init__.py
meanlib/meanlib.py
meanlib-1.0.0.dist-info/LICENSE
meanlib-1.0.0.dist-info/METADATA
meanlib-1.0.0.dist-info/WHEEL
meanlib-1.0.0.dist-info/entry_points.txt
meanlib-1.0.0.dist-info/top_level.txt
meanlib-1.0.0.dist-info/RECORD
