Metadata-Version: 2.1
Name: meanlib
Version: 1.0.0
Summary: A Python package for calculating simple and weighted means, featuring classes for dynamic updates and sliding window functionality.
Home-page: https://github.com/PinkPantherPC/meanlib.git
Author: Tobia Petrolini
License: MIT
Classifier: Programming Language :: Python :: 3
Classifier: License :: OSI Approved :: MIT License
Classifier: Operating System :: OS Independent
Classifier: Operating System :: Microsoft :: Windows
Requires-Python: >=3.7
License-File: LICENSE
Requires-Dist: numpy >=1.15.0
